{"chunk":2,"numChunks":7,"fileHash":"0iQzGoAU0H+H6xLyYWfFoCGgiAKMGgRiaRjoHR5A00s=","filePath":"project-board-sync/src/rules/linked-issues-processor.js","content":"/**\nasync function processLinkedIssues(pullRequest, projectId, currentColumn, currentSprint) {\n    const { id: pullRequestId, number: pullRequestNumber, repository: { nameWithOwner: repositoryName }, state, merged } = pullRequest;\n    const linkedIssueNodes = pullRequest.linkedIssues?.nodes || [];\n    let changed = false;\n    let reason = '';\n    const linkedIssueResults = [];\n    log.info(`Processing linked issues for PR #${pullRequestNumber} in ${repositoryName}`);\n    if (linkedIssueNodes.length === 0) {\n        reason = 'No linked issues';\n        log.info(`No linked issues found for PR #${pullRequestNumber}`);\n        return { changed, reason, linkedIssues: linkedIssueResults };\n    }\n    // Process rules for this PR\n    const ruleActions = processLinkedIssueRules(pullRequest);\n    if (ruleActions.length === 0) {\n        reason = 'No linked issue rules triggered';\n        log.info(`No linked issue rules triggered for PR #${pullRequestNumber}`);\n        return { changed, reason, linkedIssues: linkedIssueResults };\n    }\n    // Process each linked issue"}