{"chunk":26,"numChunks":53,"fileHash":"sf1/a8sy3U89ZYgXFMHk7f1nC4+cS6xae3VYARTbfgI=","filePath":"project-board-sync/test/mocks/test-board.js","content":"/**\nmodule.exports = {\n  \"items\": [\n    {\n      \"id\": \"test-gzgTlGFc\",\n      \"type\": \"ISSUE\",\n      \"content\": {\n        \"title\": \"Test Code cleanup to make sonar happy\",\n        \"number\": 21,\n        \"author\": {\n          \"login\": \"franTarkenton\"\n        },\n        \"repository\": {\n          \"nameWithOwner\": \"test-org/nr-fds-pyetl\"\n        },\n        \"state\": \"OPEN\"\n      },\n      \"fieldValues\": {\n        \"nodes\": [\n          {},\n          {},\n          {},\n          {\n            \"field\": {\n              \"name\": \"Status\"\n            },\n            \"name\": \"Backlog\"\n          },\n          {}\n        ]\n      }\n    },\n    {\n      \"id\": \"test-gzgXvL4c\",\n      \"type\": \"ISSUE\",\n      \"content\": {\n        \"title\": \"Test Test / Fix data migration tooling for openshift postgres databases.\",\n        \"number\": 17,\n        \"author\": {\n          \"login\": \"franTarkenton\"\n        },\n        \"repository\": {\n          \"nameWithOwner\": \"test-org/nr-oracle-env\"\n        },\n        \"state\": \"OPEN\"\n      },\n      \"fieldValues\": {\n        \"nodes\": [\n          {},\n          {},\n          {},\n          {\n            \"field\": {\n              \"name\": \"Status\"\n            },\n            \"name\": \"Backlog\"\n          },\n          {}\n        ]\n      }\n    },"}